point_picker/__init__.py
point_picker/cli.py
point_picker-0.1.1.dist-info/entry_points.txt
point_picker-0.1.1.dist-info/WHEEL
point_picker-0.1.1.dist-info/METADATA
point_picker-0.1.1.dist-info/RECORD
