Metadata-Version: 2.1
Name: point-picker
Version: 0.1.1
Summary: 
Author: Matthew Hartley
Author-email: mhartley@cantab.net
Requires-Python: >=3.8,<4.0
Classifier: Programming Language :: Python :: 3
Classifier: Programming Language :: Python :: 3.8
Requires-Dist: PyQt5 (>=5.15.2,<6.0.0)
Requires-Dist: click (>=7.1.2,<8.0.0)
Requires-Dist: imageio (>=2.9.0,<3.0.0)
Requires-Dist: pandas (>=1.2.2,<2.0.0)
Requires-Dist: scikit-image (>=0.18.1,<0.19.0)
Requires-Dist: vispy (>=0.6.6,<0.7.0)
